stouputils/__init__.py
stouputils/__init__.pyi
stouputils/__main__.py
stouputils/_deprecated.py
stouputils/_deprecated.pyi
stouputils/all_doctests.py
stouputils/all_doctests.pyi
stouputils/applications/__init__.py
stouputils/applications/__init__.pyi
stouputils/applications/automatic_docs.py
stouputils/applications/automatic_docs.pyi
stouputils/applications/upscaler/__init__.py
stouputils/applications/upscaler/__init__.pyi
stouputils/applications/upscaler/config.py
stouputils/applications/upscaler/config.pyi
stouputils/applications/upscaler/image.py
stouputils/applications/upscaler/image.pyi
stouputils/applications/upscaler/video.py
stouputils/applications/upscaler/video.pyi
stouputils/archive.py
stouputils/archive.pyi
stouputils/backup.py
stouputils/backup.pyi
stouputils/collections.py
stouputils/collections.pyi
stouputils/continuous_delivery/__init__.py
stouputils/continuous_delivery/__init__.pyi
stouputils/continuous_delivery/cd_utils.py
stouputils/continuous_delivery/cd_utils.pyi
stouputils/continuous_delivery/github.py
stouputils/continuous_delivery/github.pyi
stouputils/continuous_delivery/pypi.py
stouputils/continuous_delivery/pypi.pyi
stouputils/continuous_delivery/pyproject.py
stouputils/continuous_delivery/pyproject.pyi
stouputils/continuous_delivery/stubs.py
stouputils/continuous_delivery/stubs.pyi
stouputils/ctx.py
stouputils/ctx.pyi
stouputils/data_science/config/get.py
stouputils/data_science/config/set.py
stouputils/data_science/data_processing/image/__init__.py
stouputils/data_science/data_processing/image/auto_contrast.py
stouputils/data_science/data_processing/image/axis_flip.py
stouputils/data_science/data_processing/image/bias_field_correction.py
stouputils/data_science/data_processing/image/binary_threshold.py
stouputils/data_science/data_processing/image/blur.py
stouputils/data_science/data_processing/image/brightness.py
stouputils/data_science/data_processing/image/canny.py
stouputils/data_science/data_processing/image/clahe.py
stouputils-1.19.3.dist-info/WHEEL
stouputils-1.19.3.dist-info/entry_points.txt
stouputils-1.19.3.dist-info/METADATA
stouputils-1.19.3.dist-info/RECORD
