Metadata-Version: 2.3
Name: stouputils
Version: 1.19.3
Summary: Stouputils is a collection of utility modules designed to simplify and enhance the development process. It includes a range of tools for tasks such as execution of doctests, display utilities, decorators, as well as context managers, and many more.
Keywords: utilities,tools,helpers,development,python
Author: Stoupy51
Author-email: Stoupy51 <stoupy51@gmail.com>
Classifier: Programming Language :: Python :: 3
Classifier: Programming Language :: Python :: 3.12
Classifier: Programming Language :: Python :: 3.13
Classifier: Programming Language :: Python :: 3.14
Classifier: License :: OSI Approved :: MIT License
Classifier: Operating System :: OS Independent
Requires-Dist: tqdm>=4.0.0
Requires-Dist: requests>=2.20.0
Requires-Dist: msgspec[toml,yaml]>=0.20.0
Requires-Dist: pillow>=12.0.0
Requires-Dist: python-box>=7.0.0
Requires-Dist: argcomplete>=3.0.0
Requires-Dist: numpy
Requires-Dist: opencv-python ; extra == 'data-science'
Requires-Dist: scikit-image ; extra == 'data-science'
Requires-Dist: simpleitk ; extra == 'data-science'
Requires-Dist: mlflow ; extra == 'data-science'
Requires-Dist: tensorflow ; extra == 'data-science'
Requires-Dist: scikit-learn ; extra == 'data-science'
Requires-Dist: pywavelets ; extra == 'data-science'
Requires-Dist: mypy ; extra == 'docs'
Requires-Dist: myst-parser ; extra == 'docs'
Requires-Dist: sphinx-copybutton ; extra == 'docs'
Requires-Dist: sphinx-design ; extra == 'docs'
Requires-Dist: sphinx-treeview ; extra == 'docs'
Requires-Dist: sphinx-breeze-theme ; extra == 'docs'
Requires-Dist: pydata-sphinx-theme ; extra == 'docs'
Requires-Dist: redis[hiredis] ; extra == 'redis'
Requires-Python: >=3.12
Project-URL: Homepage, https://stoupy51.github.io/stouputils
Project-URL: Issues, https://github.com/Stoupy51/stouputils/issues
Project-URL: Source, https://github.com/Stoupy51/stouputils
Provides-Extra: data-science
Provides-Extra: docs
Provides-Extra: redis
